mcp_vul_cve/__init__.py
mcp_vul_cve/server.py
mcp_vul_cve-0.1.2.dist-info/WHEEL
mcp_vul_cve-0.1.2.dist-info/entry_points.txt
mcp_vul_cve-0.1.2.dist-info/METADATA
mcp_vul_cve-0.1.2.dist-info/RECORD
