Metadata-Version: 2.3
Name: mcp-vul-cve
Version: 0.1.2
Summary: Add your description here
Author: wyxxl
Author-email: wyxxl <3103089864@qq.com>
Requires-Dist: mcp[cli]>=1.13.1
Requires-Dist: requests>=2.31.0
Requires-Python: >=3.9
